spyglass_ai/__init__.py
spyglass_ai/langchain_aws.py
spyglass_ai/langchain_azure.py
spyglass_ai/langchain_openai.py
spyglass_ai/mcp_tools.py
spyglass_ai/openai.py
spyglass_ai/otel.py
spyglass_ai/pydantic.py
spyglass_ai/trace.py
spyglass_ai-0.1.8.dist-info/METADATA
spyglass_ai-0.1.8.dist-info/WHEEL
spyglass_ai-0.1.8.dist-info/licenses/LICENSE
spyglass_ai-0.1.8.dist-info/RECORD
