Metadata-Version: 2.4
Name: spyglass-ai
Version: 0.1.8
Summary: A client library for shipping telemetry to the Spyglass AI platform
Project-URL: Homepage, https://spyglass-ai.com
Project-URL: Repository, https://github.com/spyglass-ai/spyglass-sdk
Project-URL: Bug Reports, https://github.com/spyglass-ai/spyglass-sdk/issues
Project-URL: Source Code, https://github.com/spyglass-ai/spyglass-sdk
Project-URL: Changelog, https://github.com/spyglass-ai/spyglass-sdk/blob/main/CHANGELOG.md
Author-email: Spyglass AI Team <team@spyglass-ai.com>
License-Expression: MIT
License-File: LICENSE
Keywords: ai,llm,monitoring,observability,openai,opentelemetry,tracing
Classifier: Development Status :: 3 - Alpha
Classifier: Intended Audience :: Developers
Classifier: License :: OSI Approved :: MIT License
Classifier: Operating System :: OS Independent
Classifier: Programming Language :: Python :: 3
Classifier: Programming Language :: Python :: 3.12
Classifier: Topic :: Scientific/Engineering :: Artificial Intelligence
Classifier: Topic :: Software Development :: Libraries :: Python Modules
Classifier: Topic :: System :: Logging
Classifier: Topic :: System :: Monitoring
Requires-Python: >=3.12
Requires-Dist: opentelemetry-api>=1.33.1
Requires-Dist: opentelemetry-exporter-otlp-proto-http>=1.33.1
Requires-Dist: opentelemetry-sdk>=1.33.1
Provides-Extra: dev
Requires-Dist: black>=23.0.0; extra == 'dev'
Requires-Dist: flake8>=6.0.0; extra == 'dev'
Requires-Dist: isort>=5.12.0; extra == 'dev'
Requires-Dist: pytest-asyncio>=0.21.0; extra == 'dev'
Requires-Dist: pytest-cov>=4.0.0; extra == 'dev'
Requires-Dist: pytest-env>=1.1.0; extra == 'dev'
Requires-Dist: pytest-mock>=3.10.0; extra == 'dev'
Requires-Dist: pytest>=7.0.0; extra == 'dev'
Provides-Extra: langchain-aws
Requires-Dist: langchain-aws>=0.1.0; extra == 'langchain-aws'
Requires-Dist: langchain-core>=1.0.4; extra == 'langchain-aws'
Requires-Dist: python-dotenv>=1.1.1; extra == 'langchain-aws'
Provides-Extra: langchain-openai
Requires-Dist: langchain-core>=1.0.4; extra == 'langchain-openai'
Requires-Dist: langchain-openai>=1.0.2; extra == 'langchain-openai'
Provides-Extra: mcp
Requires-Dist: langchain-mcp-adapters>=0.1.0; extra == 'mcp'
Requires-Dist: mcp>=1.0.0; extra == 'mcp'
Provides-Extra: pydantic-ai
Requires-Dist: pydantic-ai>=1.14.1; extra == 'pydantic-ai'
Provides-Extra: test
Requires-Dist: pytest-asyncio>=0.21.0; extra == 'test'
Requires-Dist: pytest-cov>=4.0.0; extra == 'test'
Requires-Dist: pytest-env>=1.1.0; extra == 'test'
Requires-Dist: pytest-mock>=3.10.0; extra == 'test'
Requires-Dist: pytest>=7.0.0; extra == 'test'
